pycertauthority/CertificateAuthority.py
pycertauthority/CertificateExtensions.py
pycertauthority/CertificateUtils.py
pycertauthority/__init__.py
pycertauthority-0.0.1.dist-info/LICENSE
pycertauthority-0.0.1.dist-info/METADATA
pycertauthority-0.0.1.dist-info/WHEEL
pycertauthority-0.0.1.dist-info/top_level.txt
pycertauthority-0.0.1.dist-info/RECORD
